cmsml/__init__.py
cmsml/__meta__.py
cmsml/lazy_loader.py
cmsml/util.py
cmsml/keras/__init__.py
cmsml/keras/callbacks.py
cmsml/scripts/__init__.py
cmsml/scripts/check_aot_compatibility.py
cmsml/scripts/compile_tf_graph.py
cmsml/scripts/open_tf_graph.py
cmsml/tensorflow/__init__.py
cmsml/tensorflow/aot.py
cmsml/tensorflow/tools.py
cmsml-0.2.7.dist-info/LICENSE
cmsml-0.2.7.dist-info/METADATA
cmsml-0.2.7.dist-info/WHEEL
cmsml-0.2.7.dist-info/entry_points.txt
cmsml-0.2.7.dist-info/top_level.txt
cmsml-0.2.7.dist-info/RECORD
