Metadata-Version: 2.1
Name: cmsml
Version: 0.2.7
Summary: Python package of the CMS Machine Learning Group
Author-email: Marcel Rieger <marcel.rieger@cern.ch>
License: Copyright (c) 2020 - 2023, CMS Machine Learning Group
Keywords: CERN,CMS,LHC,machine learning,tensorflow,keras
Classifier: Programming Language :: Python
Classifier: Programming Language :: Python :: 3
Classifier: Programming Language :: Python :: 3.7
Classifier: Programming Language :: Python :: 3.8
Classifier: Programming Language :: Python :: 3.9
Classifier: Programming Language :: Python :: 3.10
Classifier: Programming Language :: Python :: 3.11
Classifier: Programming Language :: Python :: 3.12
Classifier: Development Status :: 4 - Beta
Classifier: Operating System :: OS Independent
Classifier: License :: OSI Approved :: BSD License
Classifier: Intended Audience :: Developers
Classifier: Intended Audience :: Science/Research
Classifier: Intended Audience :: Information Technology
Requires-Python: >=3.7
License-File: LICENSE
Requires-Dist: tabulate ~=0.9.0
Provides-Extra: dev
Requires-Dist: flake8-quotes ~=3.4.0 ; extra == 'dev'
Requires-Dist: pytest-xdist ~=3.4.0 ; extra == 'dev'
Requires-Dist: flake8 ~=5.0.0 ; (python_version < "3.8") and extra == 'dev'
Requires-Dist: flake8-commas ~=2.1.0 ; (python_version < "3.8") and extra == 'dev'
Requires-Dist: pytest ~=7.4.4 ; (python_version < "3.8") and extra == 'dev'
Requires-Dist: pytest-cov ~=4.1.0 ; (python_version < "3.8") and extra == 'dev'
Requires-Dist: flake8 ~=7.1.1 ; (python_version >= "3.8") and extra == 'dev'
Requires-Dist: flake8-commas ~=4.0.0 ; (python_version >= "3.8") and extra == 'dev'
Requires-Dist: pytest ~=8.3.2 ; (python_version >= "3.8") and extra == 'dev'
Requires-Dist: pytest-cov ~=5.0.0 ; (python_version >= "3.8") and extra == 'dev'
